[
  {
    "code": "08",
    "name": "Meranti"
  },
  {
    "code": "09",
    "name": "Air Joman"
  },
  {
    "code": "10",
    "name": "Tanjung Balai"
  },
  {
    "code": "11",
    "name": "Sei Kepayang"
  },
  {
    "code": "12",
    "name": "Simpang Empat"
  },
  {
    "code": "13",
    "name": "Air Batu"
  },
  {
    "code": "14",
    "name": "Pulau Rakyat"
  },
  {
    "code": "15",
    "name": "Bandar Pulau"
  },
  {
    "code": "16",
    "name": "Buntu Pane"
  },
  {
    "code": "17",
    "name": "Bandar Pasir Mandoge"
  },
  {
    "code": "18",
    "name": "Aek Kuasan"
  },
  {
    "code": "19",
    "name": "Kota Kisaran Barat"
  },
  {
    "code": "20",
    "name": "Kota Kisaran Timur"
  },
  {
    "code": "21",
    "name": "Aek Songsongan"
  },
  {
    "code": "22",
    "name": "Rahuning (Rahunig)"
  },
  {
    "code": "23",
    "name": "Sei Dadap"
  },
  {
    "code": "24",
    "name": "Sei Kepayang Barat"
  },
  {
    "code": "25",
    "name": "Sei Kepayang Timur"
  },
  {
    "code": "26",
    "name": "Tinggi Raja"
  },
  {
    "code": "27",
    "name": "Setia Janji"
  },
  {
    "code": "28",
    "name": "Silau Laut"
  },
  {
    "code": "29",
    "name": "Rawang Panca Arga"
  },
  {
    "code": "30",
    "name": "Pulo Bandring"
  },
  {
    "code": "31",
    "name": "Teluk Dalam"
  },
  {
    "code": "32",
    "name": "Aek Ledong"
  }
]