[
  {
    "code": "01",
    "name": "Sidikalang"
  },
  {
    "code": "02",
    "name": "Sumbul"
  },
  {
    "code": "03",
    "name": "Tigalingga (Tiga Lingga)"
  },
  {
    "code": "04",
    "name": "Siempat Nempu"
  },
  {
    "code": "05",
    "name": "Silima Pungga Pungga"
  },
  {
    "code": "06",
    "name": "Tanah Pinem"
  },
  {
    "code": "07",
    "name": "Siempat Nempu Hulu"
  },
  {
    "code": "08",
    "name": "Siempat Nempu Hilir"
  },
  {
    "code": "09",
    "name": "Pegagan Hilir"
  },
  {
    "code": "10",
    "name": "Parbuluan"
  },
  {
    "code": "11",
    "name": "Lae Parira"
  },
  {
    "code": "12",
    "name": "Gunung Sitember"
  },
  {
    "code": "13",
    "name": "Berampu (Brampu)"
  },
  {
    "code": "14",
    "name": "Silahisabungan (Silahi Sabungan)"
  },
  {
    "code": "15",
    "name": "Sitinjo"
  }
]